ipref/__init__.py
ipref/__main__.py
ipref/config-geolite.yaml.orig
ipref/config.py
ipref/config.yaml.orig
ipref/lookup.py
ipref/util.py
ipref/web.py
ipref/data/__init__.py
ipref/data/dns.py
ipref/data/geoip.py
ipref/static/css/bootstrap.min.css
ipref/templates/search.html
ipref-0.3.0.dist-info/METADATA
ipref-0.3.0.dist-info/WHEEL
ipref-0.3.0.dist-info/entry_points.txt
ipref-0.3.0.dist-info/top_level.txt
ipref-0.3.0.dist-info/RECORD
