Metadata-Version: 2.1
Name: ipref
Version: 0.3.0
Summary: A simple utility to lookup IP addresses by MaxMind's GeoIP databases (CLI & WEB).
Home-page: https://github.com/md-irohas/ipref-py
Author: mkt
Author-email: md.irohas@gmail.com
Project-URL: Bug Tracker, https://github.com/md-irohas/ipref-py/issues
Classifier: Programming Language :: Python :: 3
Classifier: License :: OSI Approved :: MIT License
Classifier: Operating System :: OS Independent
Requires-Python: >=3.7
Requires-Dist: dnspython
Requires-Dist: geoip2
Requires-Dist: pyyaml
Provides-Extra: dev
Requires-Dist: pytest ; extra == 'dev'
Requires-Dist: pytest-cov ; extra == 'dev'
Requires-Dist: flake8 ; extra == 'dev'
Requires-Dist: black ; extra == 'dev'
Requires-Dist: isort ; extra == 'dev'
Requires-Dist: wheel ; extra == 'dev'
Provides-Extra: web
Requires-Dist: Flask ; extra == 'web'
Requires-Dist: gunicorn ; extra == 'web'
Requires-Dist: emoji-country-flag ; extra == 'web'
